<PAMDataset>
  <PAMRasterBand band="1">
    <Histograms>
      <HistItem>
        <HistMin>-43.055581465</HistMin>
        <HistMax>190.280451465</HistMax>
        <BucketCount>1000</BucketCount>
        <IncludeOutOfRange>0</IncludeOutOfRange>
        <Approximate>1</Approximate>
        <HistCounts>19|3|0|1|0|0|1|1|0|1|1|0|0|0|0|0|0|0|0|0|0|0|0|0|1|0|0|0|3|36|2|1|0|1|6|15|1|0|1|3|0|10|6|13|5|0|1|1|1|0|2|0|2|0|0|0|1|0|2|1|0|2|0|0|0|2|2|2|0|0|1|0|1|0|0|0|0|0|0|0|0|0|1|0|0|0|1|0|0|0|1|0|0|1|1|0|0|0|1|0|0|0|1|0|0|0|0|0|0|0|0|0|0|1|0|0|1|0|0|0|0|0|0|0|0|0|1|0|0|0|1|0|0|1|0|1|1|1|1|0|0|0|1|0|0|0|0|0|0|0|0|0|0|1|1|0|0|0|0|0|0|2|0|0|1|0|2|1|1|3|2|2|0|0|0|0|1|1|0|8|130|1942|5987|6745|2468|364|62|23|19|26|12|19|24|23|23|31|22|25|24|38|31|32|38|35|55|37|76|87|87|89|92|111|120|168|217|210|210|260|274|202|201|174|196|163|150|184|148|145|138|145|137|128|125|114|124|124|160|169|178|192|187|188|199|214|218|204|253|329|313|340|346|427|415|431|445|405|360|325|376|388|349|376|433|369|356|322|282|289|271|251|233|241|210|199|223|177|176|154|184|175|179|186|191|152|143|150|137|136|122|114|113|143|142|145|147|148|135|134|140|166|138|124|171|136|139|142|137|102|123|134|124|108|94|133|132|139|128|108|101|121|121|146|131|117|110|109|98|102|80|92|80|99|86|108|107|86|120|100|95|88|121|95|56|89|63|71|67|71|62|77|65|61|79|60|62|53|57|54|65|56|40|51|57|73|41|50|36|46|45|37|56|58|33|52|63|44|45|41|46|30|42|56|51|50|42|38|35|40|36|40|37|46|36|30|35|39|38|46|52|41|37|48|52|43|37|43|33|37|32|38|24|31|27|32|37|27|23|24|30|23|35|24|19|21|20|25|23|17|23|22|19|21|18|14|20|18|13|15|15|9|12|16|9|17|11|11|17|12|16|18|16|15|18|22|22|21|9|14|16|13|15|6|13|12|16|11|6|9|9|9|4|4|1|7|6|9|9|22|21|18|12|10|3|10|10|5|11|4|8|11|9|6|6|10|7|12|11|10|10|14|19|8|7|7|7|4|4|2|3|6|3|4|4|4|6|5|4|5|4|3|1|7|2|2|2|3|5|5|1|6|3|6|0|3|2|2|2|2|3|16|33|13|4|4|7|4|2|1|2|1|4|7|4|5|6|3|1|4|1|2|1|1|2|2|2|3|4|2|1|1|2|2|2|0|2|1|1|0|4|0|4|2|0|2|1|0|0|0|0|0|0|0|2|3|1|1|1|1|0|0|1|1|2|0|4|9|3|3|3|5|4|4|4|4|0|3|1|1|1|2|1|0|1|3|0|0|2|3|0|1|1|0|2|2|0|2|0|0|0|0|0|0|0|0|0|0|0|1|0|0|1|2|1|0|0|0|1|2|0|0|0|3|0|0|1|2|1|0|0|0|0|2|0|1|1|0|0|0|0|1|0|0|0|1|1|0|0|0|1|0|0|0|0|0|0|0|0|0|1|0|0|0|2|0|0|0|0|0|1|0|0|0|0|0|0|0|0|1|0|1|2|0|0|4|1|1|0|0|0|1|1|0|0|0|0|0|1|0|0|0|0|0|1|4|3|2|2|2|3|2|2|1|0|2|2|3|2|1|1|0|0|0|0|1|0|0|0|0|0|0|0|0|2|1|0|0|0|0|0|0|0|1|6|0|0|1|0|0|0|0|0|0|0|0|0|0|0|0|0|0|0|0|1|0|0|0|1|0|0|0|0|0|0|1|1|1|2|1|1|2|0|0|0|0|0|0|0|0|0|0|0|0|0|0|0|1|0|0|0|0|0|0|0|0|0|0|0|0|0|0|0|0|0|0|0|0|0|0|0|0|0|0|0|0|0|0|0|0|0|0|0|0|0|0|0|0|0|0|0|0|0|0|0|0|0|0|0|0|0|0|0|0|0|0|0|0|0|0|0|0|0|0|0|0|0|0|0|0|0|0|0|0|0|0|0|0|0|0|0|0|0|0|0|0|0|0|0|0|0|0|0|0|0|0|0|0|0|0|0|0|0|0|0|0|0|0|0|0|0|0|0|0|0|0|0|0|0|0|0|0|0|0|0|0|0|0|0|0|0|0|0|0|0|0|0|0|0|0|0|0|0|0|0|0|0|0|0|0|0|0|1|0|0|0|0|0|0|0|0|1</HistCounts>
      </HistItem>
    </Histograms>
    <Metadata>
      <MDI key="STATISTICS_MAXIMUM">190.1639</MDI>
      <MDI key="STATISTICS_MEAN">15.34344247804</MDI>
      <MDI key="STATISTICS_MINIMUM">-42.93903</MDI>
      <MDI key="STATISTICS_STDDEV">18.055450515794</MDI>
    </Metadata>
  </PAMRasterBand>
</PAMDataset>
